hangul_checker/__init__.py
hangul_checker/hangul_checker.py
tests/__init__.py
tests/test_hangul_checker.py
py_hangul_checker-0.2.0.dist-info/AUTHORS.md
py_hangul_checker-0.2.0.dist-info/LICENSE
py_hangul_checker-0.2.0.dist-info/METADATA
py_hangul_checker-0.2.0.dist-info/WHEEL
py_hangul_checker-0.2.0.dist-info/top_level.txt
py_hangul_checker-0.2.0.dist-info/RECORD
