Metadata-Version: 2.1
Name: py-hangul-checker
Version: 0.2.0
Summary: Python implementation of Hanhul (Korean Language) Spell Checker
Home-page: https://github.com/jha929/py-hangul-checker
Author: Jinsung Ha
Author-email: jsung5381@naver.com
License: MIT
Platform: UNKNOWN
Classifier: Programming Language :: Python :: 3
Classifier: License :: OSI Approved :: MIT License
Classifier: Operating System :: OS Independent
Requires-Dist: requests
Requires-Dist: beautifulsoup4
